hegelion/__init__.py
hegelion/core/__init__.py
hegelion/core/autocoding_state.py
hegelion/core/constants.py
hegelion/core/prompt_autocoding.py
hegelion/core/prompt_dialectic.py
hegelion/mcp/__init__.py
hegelion/mcp/constants.py
hegelion/mcp/progress.py
hegelion/mcp/response.py
hegelion/mcp/server.py
hegelion/mcp/tooling.py
hegelion/mcp/validation.py
hegelion/mcp/handlers/__init__.py
hegelion/mcp/handlers/autocoding.py
hegelion/mcp/handlers/dialectic.py
hegelion/scripts/mcp_setup.py
hegelion-0.4.4.dist-info/licenses/LICENSE
hegelion-0.4.4.dist-info/METADATA
hegelion-0.4.4.dist-info/WHEEL
hegelion-0.4.4.dist-info/entry_points.txt
hegelion-0.4.4.dist-info/top_level.txt
hegelion-0.4.4.dist-info/RECORD
