Metadata-Version: 2.4
Name: hegelion
Version: 0.4.4
Summary: Prompt-driven dialectical reasoning and autocoding for LLMs (thesis -> antithesis -> synthesis)
Author-email: Hunter Bown <hunter@shannonlabs.dev>
License-Expression: MIT
Project-URL: Homepage, https://github.com/Hmbown/Hegelion
Project-URL: Repository, https://github.com/Hmbown/Hegelion
Project-URL: Documentation, https://github.com/Hmbown/Hegelion/blob/main/docs/HEGELION_SPEC.md
Project-URL: Bug Tracker, https://github.com/Hmbown/Hegelion/issues
Keywords: ai,llm,reasoning,dialectical,hegelian,mcp,autocoding,prompt,agent,cursor,vscode,copilot,anthropic,openai,claude,gpt,ollama,gemini
Classifier: Development Status :: 4 - Beta
Classifier: Intended Audience :: Developers
Classifier: Intended Audience :: Science/Research
Classifier: Programming Language :: Python :: 3
Classifier: Programming Language :: Python :: 3.10
Classifier: Programming Language :: Python :: 3.11
Classifier: Programming Language :: Python :: 3.12
Classifier: Topic :: Scientific/Engineering :: Artificial Intelligence
Classifier: Topic :: Software Development :: Libraries :: Python Modules
Requires-Python: >=3.10
License-File: LICENSE
Requires-Dist: mcp>=1.21.1
Requires-Dist: anyio>=4.0.0
Provides-Extra: dev
Requires-Dist: pytest>=7.0; extra == "dev"
Requires-Dist: pytest-asyncio>=0.21; extra == "dev"
Requires-Dist: pytest-cov>=4.0; extra == "dev"
Requires-Dist: black>=23.0; extra == "dev"
Requires-Dist: ruff>=0.1.0; extra == "dev"
Requires-Dist: pre-commit>=3.0; extra == "dev"
Requires-Dist: build>=1.0.0; extra == "dev"
Requires-Dist: twine>=5.0.0; extra == "dev"
Dynamic: license-file
